graphscraper/__init__.py
graphscraper/base.py
graphscraper/db.py
graphscraper/demo.py
graphscraper/eventdispatcher.py
graphscraper/igraphwrapper.py
graphscraper/spotifyartist.py
graphscraper-0.5.0.dist-info/LICENSE.txt
graphscraper-0.5.0.dist-info/METADATA
graphscraper-0.5.0.dist-info/WHEEL
graphscraper-0.5.0.dist-info/top_level.txt
graphscraper-0.5.0.dist-info/RECORD
