Metadata-Version: 2.1
Name: graphscraper
Version: 0.5.0
Summary: Graph implementation that loads graph data (nodes and edges) from external sources and caches the loaded data in a database using sqlalchemy or flask-sqlalchemy.
Home-page: https://github.com/volfpeter/graphscraper
Author: Peter Volf
Author-email: do.volfp@gmail.com
License: MIT
Keywords: graph network webscraping sqlalchemy database db caching
Platform: UNKNOWN
Classifier: Development Status :: 4 - Beta
Classifier: Intended Audience :: Developers
Classifier: Intended Audience :: Information Technology
Classifier: Intended Audience :: Science/Research
Classifier: License :: OSI Approved :: MIT License
Classifier: Natural Language :: English
Classifier: Programming Language :: Python :: 3
Classifier: Topic :: Database
Classifier: Topic :: Internet
Classifier: Topic :: Scientific/Engineering
Classifier: Topic :: Software Development :: Libraries
Classifier: Topic :: Utilities
Requires-Python: >=3
Requires-Dist: sqlalchemy (>=1.3)
